[
  { "id": "k1", "name": "Казик 1",  "image": "data:image/svg+xml;utf8,<svg xmlns='http://www.w3.org/2000/svg' width='800' height='400'><defs><linearGradient id='g' x1='0' x2='1'><stop offset='0' stop-color='%23395cff'/><stop offset='1' stop-color='%2300ffd8'/></linearGradient></defs><rect width='100%' height='100%' fill='url(%23g)'/><text x='50%' y='52%' dominant-baseline='middle' text-anchor='middle' font-size='56' font-family='Arial' fill='%23081012'>КАЗИК</text></svg>", "bonus":"Бонус: демонстрация", "promo_code":"KZ1", "url":"#", "categories":["Топ"] },
  { "id": "k2", "name": "Казик 2",  "image": "data:image/svg+xml;utf8,<svg xmlns='http://www.w3.org/2000/svg' width='800' height='400'><defs><linearGradient id='g2' x1='0' x2='1'><stop offset='0' stop-color='%23ff5a9e'/><stop offset='1' stop-color='%23ffb36b'/></linearGradient></defs><rect width='100%' height='100%' fill='url(%23g2)'/><text x='50%' y='52%' dominant-baseline='middle' text-anchor='middle' font-size='56' font-family='Arial' fill='%23081012'>КАЗИК</text></svg>", "bonus":"Фриспины +500", "promo_code":"KZ2", "url":"#", "categories":["Рекомендуем"] },
  { "id": "k3", "name": "Казик 3",  "image": "data:image/svg+xml;utf8,<svg xmlns='http://www.w3.org/2000/svg' width='800' height='400'><defs><linearGradient id='g3' x1='0' x2='1'><stop offset='0' stop-color='%2322f0ff'/><stop offset='1' stop-color='%237a5cff'/></linearGradient></defs><rect width='100%' height='100%' fill='url(%23g3)'/><text x='50%' y='52%' dominant-baseline='middle' text-anchor='middle' font-size='56' font-family='Arial' fill='%23081012'>КАЗИК</text></svg>", "bonus":"Крипто-бонус", "promo_code":"KZ3", "url":"#", "categories":["Крипто"] },
  { "id": "k4", "name": "Казик 4",  "image": "data:image/svg+xml;utf8,<svg xmlns='http://www.w3.org/2000/svg' width='800' height='400'><defs><linearGradient id='g4' x1='0' x2='1'><stop offset='0' stop-color='%23ffe066'/><stop offset='1' stop-color='%23ff7aa2'/></linearGradient></defs><rect width='100%' height='100%' fill='url(%23g4)'/><text x='50%' y='52%' dominant-baseline='middle' text-anchor='middle' font-size='56' font-family='Arial' fill='%23081012'>КАЗИК</text></svg>", "bonus":"Бонус доступен", "promo_code":"KZ4", "url":"#", "categories":["Топ"] },
  { "id": "k5", "name": "Казик 5",  "image": "data:image/svg+xml;utf8,<svg xmlns='http://www.w3.org/2000/svg' width='800' height='400'><defs><linearGradient id='g5' x1='0' x2='1'><stop offset='0' stop-color='%2300ffd8'/><stop offset='1' stop-color='%237a5cff'/></linearGradient></defs><rect width='100%' height='100%' fill='url(%23g5)'/><text x='50%' y='52%' dominant-baseline='middle' text-anchor='middle' font-size='56' font-family='Arial' fill='%23081012'>КАЗИК</text></svg>", "bonus":"Экстра оффер", "promo_code":"KZ5", "url":"#", "categories":["Рекомендуем"] },
  { "id": "k6", "name": "Казик 6",  "image": "data:image/svg+xml;utf8,<svg xmlns='http://www.w3.org/2000/svg' width='800' height='400'><defs><linearGradient id='g6' x1='0' x2='1'><stop offset='0' stop-color='%23ff5a9e'/><stop offset='1' stop-color='%2388f0ff'/></linearGradient></defs><rect width='100%' height='100%' fill='url(%23g6)'/><text x='50%' y='52%' dominant-baseline='middle' text-anchor='middle' font-size='56' font-family='Arial' fill='%23081012'>КАЗИК</text></svg>", "bonus":"Подарок при входе", "promo_code":"KZ6", "url":"#", "categories":["Крипто"] },
  { "id": "k7", "name": "Казик 7",  "image": "data:image/svg+xml;utf8,<svg xmlns='http://www.w3.org/2000/svg' width='800' height='400'><defs><linearGradient id='g7' x1='0' x2='1'><stop offset='0' stop-color='%23b38bff'/><stop offset='1' stop-color='%23ff7a9b'/></linearGradient></defs><rect width='100%' height='100%' fill='url(%23g7)'/><text x='50%' y='52%' dominant-baseline='middle' text-anchor='middle' font-size='56' font-family='Arial' fill='%23081012'>КАЗИК</text></svg>", "bonus":"Эксклюзив", "promo_code":"KZ7", "url":"#", "categories":["Топ"] },
  { "id": "k8", "name": "Казик 8",  "image": "data:image/svg+xml;utf8,<svg xmlns='http://www.w3.org/2000/svg' width='800' height='400'><defs><linearGradient id='g8' x1='0' x2='1'><stop offset='0' stop-color='%2335f0ff'/><stop offset='1' stop-color='%23ff8fb1'/></linearGradient></defs><rect width='100%' height='100%' fill='url(%23g8)'/><text x='50%' y='52%' dominant-baseline='middle' text-anchor='middle' font-size='56' font-family='Arial' fill='%23081012'>КАЗИК</text></svg>", "bonus":"Лучшее предложение", "promo_code":"KZ8", "url":"#", "categories":["Рекомендуем"] },
  { "id": "k9", "name": "Казик 9",  "image": "data:image/svg+xml;utf8,<svg xmlns='http://www.w3.org/2000/svg' width='800' height='400'><defs><linearGradient id='g9' x1='0' x2='1'><stop offset='0' stop-color='%23ffd699'/><stop offset='1' stop-color='%23b38bff'/></linearGradient></defs><rect width='100%' height='100%' fill='url(%23g9)'/><text x='50%' y='52%' dominant-baseline='middle' text-anchor='middle' font-size='56' font-family='Arial' fill='%23081012'>КАЗИК</text></svg>", "bonus":"Фриспины в подарок", "promo_code":"KZ9", "url":"#", "categories":["Крипто"] },
  { "id": "k10","name": "Казик 10", "image": "data:image/svg+xml;utf8,<svg xmlns='http://www.w3.org/2000/svg' width='800' height='400'><defs><linearGradient id='g10' x1='0' x2='1'><stop offset='0' stop-color='%2300ffd8'/><stop offset='1' stop-color='%23ff5a9e'/></linearGradient></defs><rect width='100%' height='100%' fill='url(%23g10)'/><text x='50%' y='52%' dominant-baseline='middle' text-anchor='middle' font-size='56' font-family='Arial' fill='%23081012'>КАЗИК</text></svg>", "bonus":"Приветственный бонус", "promo_code":"KZ10","url":"#","categories":["Рекомендуем"] },
  { "id": "k11","name": "Казик 11", "image": "data:image/svg+xml;utf8,<svg xmlns='http://www.w3.org/2000/svg' width='800' height='400'><defs><linearGradient id='g11' x1='0' x2='1'><stop offset='0' stop-color='%23ffb36b'/><stop offset='1' stop-color='%237a5cff'/></linearGradient></defs><rect width='100%' height='100%' fill='url(%23g11)'/><text x='50%' y='52%' dominant-baseline='middle' text-anchor='middle' font-size='56' font-family='Arial' fill='%23081012'>КАЗИК</text></svg>", "bonus":"Промо-акция", "promo_code":"KZ11","url":"#","categories":["Топ"] },
  { "id": "k12","name": "Казик 12", "image": "data:image/svg+xml;utf8,<svg xmlns='http://www.w3.org/2000/svg' width='800' height='400'><defs><linearGradient id='g12' x1='0' x2='1'><stop offset='0' stop-color='%237afcff'/><stop offset='1' stop-color='%23ff8fb1'/></linearGradient></defs><rect width='100%' height='100%' fill='url(%23g12)'/><text x='50%' y='52%' dominant-baseline='middle' text-anchor='middle' font-size='56' font-family='Arial' fill='%23081012'>КАЗИК</text></svg>", "bonus":"Сюрприз при депозите", "promo_code":"KZ12","url":"#","categories":["Рекомендуем"] },
  { "id": "scam","name":"Скам","image":"data:image/svg+xml;utf8,<svg xmlns='http://www.w3.org/2000/svg' width='800' height='400'><rect width='100%' height='100%' fill='%23ff3333'/><text x='50%' y='52%' dominant-baseline='middle' text-anchor='middle' font-size='84' font-family='Arial' fill='%23fff'>SCAM</text></svg>", "bonus":"Никакого скама! Только проверенные места!","url":"#", "fake": true, "categories": [] }
]
